logikal_browser/__init__.py
logikal_browser/browser.py
logikal_browser/chrome.py
logikal_browser/chromium.py
logikal_browser/config.py
logikal_browser/edge.py
logikal_browser/install.py
logikal_browser/py.typed
logikal_browser/scenarios.py
logikal_browser/utils.py
logikal_browser-3.1.1.dist-info/licenses/LICENSE.txt
logikal_browser-3.1.1.dist-info/METADATA
logikal_browser-3.1.1.dist-info/WHEEL
logikal_browser-3.1.1.dist-info/top_level.txt
logikal_browser-3.1.1.dist-info/RECORD
